inpost/__init__.py
inpost/api.py
inpost/static/__init__.py
inpost/static/endpoints.py
inpost/static/exceptions.py
inpost/static/friends.py
inpost/static/headers.py
inpost/static/notifications.py
inpost/static/parcels.py
inpost/static/statuses.py
inpost-0.1.5.dist-info/WHEEL
inpost-0.1.5.dist-info/METADATA
inpost-0.1.5.dist-info/LICENSE
inpost-0.1.5.dist-info/RECORD
